tm_remote_build/__init__.py
tm_remote_build/api.py
tm_remote_build/changelog.md
tm_remote_build/cli.py
tm_remote_build/log.py
tm_remote_build-2.0.0.dist-info/entry_points.txt
tm_remote_build-2.0.0.dist-info/LICENSE
tm_remote_build-2.0.0.dist-info/METADATA
tm_remote_build-2.0.0.dist-info/WHEEL
tm_remote_build-2.0.0.dist-info/RECORD
